viperlog/__init__.py
viperlog/builders.py
viperlog/core.py
viperlog/logger.py
viperlog/types.py
viperlog/viperlog.py
viperlog/viperlog_fn.py
viperlog/filters/__init__.py
viperlog/filters/base.py
viperlog/filters/package.py
viperlog/formatters/__init__.py
viperlog/formatters/base.py
viperlog/formatters/basic.py
viperlog/formatters/dict_formatter.py
viperlog/formatters/json_object.py
viperlog/formatters/json_string.py
viperlog/formatters/template.py
viperlog/handlers/__init__.py
viperlog/handlers/viperhandler.py
viperlog/processors/__init__.py
viperlog/processors/base.py
viperlog/processors/base_generic.py
viperlog/processors/base_string.py
viperlog/processors/file_processor.py
viperlog/processors/rolling_file_processor.py
viperlog/processors/console/__init__.py
viperlog/processors/dnxlogger/__init__.py
viperlog/processors/http/__init__.py
viperlog/util/__init__.py
viperlog/util/json_util.py
viperlog-0.2.102.dist-info/METADATA
viperlog-0.2.102.dist-info/WHEEL
viperlog-0.2.102.dist-info/top_level.txt
viperlog-0.2.102.dist-info/RECORD
