Metadata-Version: 2.4
Name: viperlog
Version: 0.2.102
Summary: ViperLog core logging package
License-Expression: MIT
Requires-Python: >=3.12
Provides-Extra: core
Requires-Dist: viperlog; extra == "core"
Provides-Extra: console
Requires-Dist: viperlog-console-plugin==0.2.102; extra == "console"
Provides-Extra: http
Requires-Dist: viperlog-http-plugin==0.2.102; extra == "http"
Provides-Extra: dnxlogging
Requires-Dist: viperlog-dnxlogger-plugin==0.2.102; extra == "dnxlogging"
Provides-Extra: all
Requires-Dist: viperlog-console-plugin==0.2.102; extra == "all"
Requires-Dist: viperlog-http-plugin==0.2.102; extra == "all"
Requires-Dist: viperlog-dnxlogger-plugin==0.2.102; extra == "all"
